<?xml version="1.0" encoding="UTF-8"?>
<export version="D">
  <design>
    <source>/media/david/Nano/Nano/jarwis/jarvis_shield.sch</source>
    <date>mié 01 ago 2018 10:44:28 CEST</date>
    <tool>Eeschema 4.0.7-e2-6376~58~ubuntu16.04.1</tool>
    <sheet number="1" name="/" tstamps="/">
      <title_block>
        <title>Jarwis</title>
        <company>Trastejant</company>
        <rev>0.1</rev>
        <date>2018-04-11</date>
        <source>jarvis_shield.sch</source>
        <comment number="1" value="Módulo Jarwis"/>
        <comment number="2" value="by Nano"/>
        <comment number="3" value=""/>
        <comment number="4" value=""/>
      </title_block>
    </sheet>
  </design>
  <components>
    <comp ref="D1">
      <value>LED</value>
      <footprint>LEDs:LED_0805_HandSoldering</footprint>
      <libsource lib="device" part="LED"/>
      <sheetpath names="/" tstamps="/"/>
      <tstamp>5A5DDC3D</tstamp>
    </comp>
    <comp ref="R1">
      <value>R</value>
      <footprint>Resistors_SMD:R_0805_HandSoldering</footprint>
      <libsource lib="device" part="R"/>
      <sheetpath names="/" tstamps="/"/>
      <tstamp>5A5DDD87</tstamp>
    </comp>
    <comp ref="SW1">
      <value>SW_Push</value>
      <footprint>Buttons_Switches_THT:SW_PUSH_6mm</footprint>
      <libsource lib="Switch" part="SW_Push"/>
      <sheetpath names="/" tstamps="/"/>
      <tstamp>5A605AFD</tstamp>
    </comp>
    <comp ref="SW2">
      <value>SW_Push</value>
      <footprint>Buttons_Switches_THT:SW_PUSH_6mm</footprint>
      <libsource lib="Switch" part="SW_Push"/>
      <sheetpath names="/" tstamps="/"/>
      <tstamp>5A605C1E</tstamp>
    </comp>
    <comp ref="SW3">
      <value>SW_Push</value>
      <footprint>Buttons_Switches_THT:SW_PUSH_6mm</footprint>
      <libsource lib="Switch" part="SW_Push"/>
      <sheetpath names="/" tstamps="/"/>
      <tstamp>5A605CCB</tstamp>
    </comp>
    <comp ref="R4">
      <value>10K</value>
      <footprint>Resistors_SMD:R_0805_HandSoldering</footprint>
      <libsource lib="device" part="R"/>
      <sheetpath names="/" tstamps="/"/>
      <tstamp>5A6062EA</tstamp>
    </comp>
    <comp ref="R3">
      <value>10K</value>
      <footprint>Resistors_SMD:R_0805_HandSoldering</footprint>
      <libsource lib="device" part="R"/>
      <sheetpath names="/" tstamps="/"/>
      <tstamp>5A606389</tstamp>
    </comp>
    <comp ref="R2">
      <value>10K</value>
      <footprint>Resistors_SMD:R_0805_HandSoldering</footprint>
      <datasheet>https://www.mouser.es/datasheet/2/392/n_catalog_partition23_en-1116117.pdf</datasheet>
      <fields>
        <field name="Mouser REF">754-RS2012P-103-DT53 </field>
      </fields>
      <libsource lib="device" part="R"/>
      <sheetpath names="/" tstamps="/"/>
      <tstamp>5A6063E4</tstamp>
    </comp>
    <comp ref="J1">
      <value>Screw_Terminal_1x02</value>
      <footprint>Connectors_Terminal_Blocks:TerminalBlock_bornier-2_P5.08mm</footprint>
      <libsource lib="jarvis_shield-cache" part="Screw_Terminal_1x02"/>
      <sheetpath names="/" tstamps="/"/>
      <tstamp>5A607BA9</tstamp>
    </comp>
    <comp ref="R6">
      <value>10K</value>
      <footprint>Resistors_SMD:R_0805_HandSoldering</footprint>
      <libsource lib="device" part="R"/>
      <sheetpath names="/" tstamps="/"/>
      <tstamp>5A609A45</tstamp>
    </comp>
    <comp ref="R5">
      <value>180R</value>
      <footprint>Resistors_SMD:R_0805_HandSoldering</footprint>
      <libsource lib="device" part="R"/>
      <sheetpath names="/" tstamps="/"/>
      <tstamp>5A609B1E</tstamp>
    </comp>
    <comp ref="JP1">
      <value>Jumper_NO_Small</value>
      <footprint>Pin_Headers:Pin_Header_Straight_1x02_Pitch2.54mm</footprint>
      <libsource lib="device" part="Jumper_NO_Small"/>
      <sheetpath names="/" tstamps="/"/>
      <tstamp>5A699754</tstamp>
    </comp>
    <comp ref="D2">
      <value>LED</value>
      <footprint>LEDs:LED_0805_HandSoldering</footprint>
      <libsource lib="device" part="LED"/>
      <sheetpath names="/" tstamps="/"/>
      <tstamp>5A699A67</tstamp>
    </comp>
    <comp ref="C2">
      <value>100nF</value>
      <footprint>Capacitors_SMD:C_0805_HandSoldering</footprint>
      <libsource lib="device" part="C_Small"/>
      <sheetpath names="/" tstamps="/"/>
      <tstamp>5A6A0271</tstamp>
    </comp>
    <comp ref="D4">
      <value>Neopixel_THT</value>
      <footprint>LEDs:LED_WS2812B-PLCC4</footprint>
      <libsource lib="LED" part="Neopixel_THT"/>
      <sheetpath names="/" tstamps="/"/>
      <tstamp>5A72D00C</tstamp>
    </comp>
    <comp ref="D5">
      <value>Neopixel_THT</value>
      <footprint>LEDs:LED_WS2812B-PLCC4</footprint>
      <libsource lib="LED" part="Neopixel_THT"/>
      <sheetpath names="/" tstamps="/"/>
      <tstamp>5A72D081</tstamp>
    </comp>
    <comp ref="D6">
      <value>Neopixel_THT</value>
      <footprint>LEDs:LED_WS2812B-PLCC4</footprint>
      <libsource lib="LED" part="Neopixel_THT"/>
      <sheetpath names="/" tstamps="/"/>
      <tstamp>5A72D0D8</tstamp>
    </comp>
    <comp ref="D3">
      <value>Neopixel_THT</value>
      <footprint>LEDs:LED_WS2812B-PLCC4</footprint>
      <libsource lib="LED" part="Neopixel_THT"/>
      <sheetpath names="/" tstamps="/"/>
      <tstamp>5A72D306</tstamp>
    </comp>
    <comp ref="R12">
      <value>150</value>
      <footprint>Resistors_SMD:R_0805_HandSoldering</footprint>
      <libsource lib="device" part="R"/>
      <sheetpath names="/" tstamps="/"/>
      <tstamp>5A73BA68</tstamp>
    </comp>
    <comp ref="R13">
      <value>150</value>
      <footprint>Resistors_SMD:R_0805_HandSoldering</footprint>
      <libsource lib="device" part="R"/>
      <sheetpath names="/" tstamps="/"/>
      <tstamp>5A73C235</tstamp>
    </comp>
    <comp ref="R14">
      <value>150</value>
      <footprint>Resistors_SMD:R_0805_HandSoldering</footprint>
      <libsource lib="device" part="R"/>
      <sheetpath names="/" tstamps="/"/>
      <tstamp>5A73C2B6</tstamp>
    </comp>
    <comp ref="R11">
      <value>150</value>
      <footprint>Resistors_SMD:R_0805_HandSoldering</footprint>
      <libsource lib="device" part="R"/>
      <sheetpath names="/" tstamps="/"/>
      <tstamp>5A73C6DD</tstamp>
    </comp>
    <comp ref="C4">
      <value>104</value>
      <footprint>Capacitors_SMD:C_0805_HandSoldering</footprint>
      <libsource lib="device" part="C"/>
      <sheetpath names="/" tstamps="/"/>
      <tstamp>5A742913</tstamp>
    </comp>
    <comp ref="C5">
      <value>104</value>
      <footprint>Capacitors_SMD:C_0805_HandSoldering</footprint>
      <libsource lib="device" part="C"/>
      <sheetpath names="/" tstamps="/"/>
      <tstamp>5A742990</tstamp>
    </comp>
    <comp ref="C6">
      <value>104</value>
      <footprint>Capacitors_SMD:C_0805_HandSoldering</footprint>
      <libsource lib="device" part="C"/>
      <sheetpath names="/" tstamps="/"/>
      <tstamp>5A744E57</tstamp>
    </comp>
    <comp ref="C3">
      <value>104</value>
      <footprint>Capacitors_SMD:C_0805_HandSoldering</footprint>
      <libsource lib="device" part="C"/>
      <sheetpath names="/" tstamps="/"/>
      <tstamp>5A7428A4</tstamp>
    </comp>
    <comp ref="J3">
      <value>USB_A</value>
      <footprint>Connectors:USB_A</footprint>
      <libsource lib="conn" part="USB_A"/>
      <sheetpath names="/" tstamps="/"/>
      <tstamp>5A7544DC</tstamp>
    </comp>
    <comp ref="U3">
      <value>oledDisplay</value>
      <footprint>oled_display_:oled_display_0.96</footprint>
      <datasheet>DOCUMENTATION</datasheet>
      <libsource lib="jarvis_shield-rescue" part="oledDisplay-RESCUE-jarvis_shield"/>
      <sheetpath names="/" tstamps="/"/>
      <tstamp>5A854953</tstamp>
    </comp>
    <comp ref="R15">
      <value>1K</value>
      <footprint>Resistors_SMD:R_0805_HandSoldering</footprint>
      <libsource lib="device" part="R"/>
      <sheetpath names="/" tstamps="/"/>
      <tstamp>5A8D380B</tstamp>
    </comp>
    <comp ref="R16">
      <value>2K</value>
      <footprint>Resistors_SMD:R_0805_HandSoldering</footprint>
      <libsource lib="device" part="R"/>
      <sheetpath names="/" tstamps="/"/>
      <tstamp>5A8D3878</tstamp>
    </comp>
    <comp ref="U2">
      <value>SHT30-DIS-B</value>
      <footprint>SHT30-DIS-B:DFN250X250X100-9N</footprint>
      <datasheet>http://www.mouser.com/ds/2/682/Sensirion_Humidity_Sensors_SHT3x_Datasheet_digital-971521.pdf</datasheet>
      <fields>
        <field name="Field4">2.15 USD</field>
        <field name="Field5">SENSOR HUMID/TEMP 5V I2C 3% SMD</field>
        <field name="Field6">DFN-8 Sensirion</field>
        <field name="Field7">SHT30-DIS-B</field>
        <field name="Field8">Sensirion</field>
        <field name="Mouser_REF">403-SHT30-ARP-B</field>
      </fields>
      <libsource lib="SHT30-DIS-B" part="SHT30-DIS-B"/>
      <sheetpath names="/" tstamps="/"/>
      <tstamp>5A9730B7</tstamp>
    </comp>
    <comp ref="R10">
      <value>10K</value>
      <footprint>Resistors_SMD:R_0805_HandSoldering</footprint>
      <libsource lib="device" part="R"/>
      <sheetpath names="/" tstamps="/"/>
      <tstamp>5A97426B</tstamp>
    </comp>
    <comp ref="R17">
      <value>10K</value>
      <footprint>Resistors_SMD:R_0805_HandSoldering</footprint>
      <libsource lib="device" part="R"/>
      <sheetpath names="/" tstamps="/"/>
      <tstamp>5A97435A</tstamp>
    </comp>
    <comp ref="U1">
      <value>BH1750</value>
      <footprint>BH1750FVI-TR:SOTFL50P300X75-6N</footprint>
      <datasheet>https://www.mouser.com/catalog/specsheets/Rohm_11162017_ROHMS34826-1.pdf</datasheet>
      <fields>
        <field name="MOUSER REF">755-BH1750FVI-TR</field>
      </fields>
      <libsource lib="BH1750" part="BH1750"/>
      <sheetpath names="/" tstamps="/"/>
      <tstamp>5A97BB27</tstamp>
    </comp>
    <comp ref="R8">
      <value>4.7K</value>
      <footprint>Resistors_SMD:R_0805_HandSoldering</footprint>
      <libsource lib="device" part="R"/>
      <sheetpath names="/" tstamps="/"/>
      <tstamp>5A97D347</tstamp>
    </comp>
    <comp ref="R9">
      <value>1K</value>
      <footprint>Resistors_SMD:R_0805_HandSoldering</footprint>
      <libsource lib="device" part="R"/>
      <sheetpath names="/" tstamps="/"/>
      <tstamp>5A97D5BA</tstamp>
    </comp>
    <comp ref="C1">
      <value>0.1uF</value>
      <footprint>Capacitors_SMD:C_0805_HandSoldering</footprint>
      <libsource lib="device" part="C"/>
      <sheetpath names="/" tstamps="/"/>
      <tstamp>5A97D7A7</tstamp>
    </comp>
    <comp ref="U4">
      <value>ESP-12E</value>
      <footprint>RF_Modules:ESP-12E</footprint>
      <libsource lib="jarvis_shield-cache" part="ESP-12E"/>
      <sheetpath names="/" tstamps="/"/>
      <tstamp>5AC3E83C</tstamp>
    </comp>
    <comp ref="C7">
      <value>C</value>
      <footprint>Capacitors_SMD:C_0805_HandSoldering</footprint>
      <libsource lib="device" part="C"/>
      <sheetpath names="/" tstamps="/"/>
      <tstamp>5AC49768</tstamp>
    </comp>
    <comp ref="C8">
      <value>C</value>
      <footprint>Capacitors_SMD:C_0805_HandSoldering</footprint>
      <libsource lib="device" part="C"/>
      <sheetpath names="/" tstamps="/"/>
      <tstamp>5AC497F7</tstamp>
    </comp>
    <comp ref="SW4">
      <value>SW_Push</value>
      <footprint>Buttons_Switches_SMD:SW_SPST_SKQG</footprint>
      <libsource lib="Switch" part="SW_Push"/>
      <sheetpath names="/" tstamps="/"/>
      <tstamp>5AC4AA50</tstamp>
    </comp>
    <comp ref="R19">
      <value>100R</value>
      <footprint>Resistors_SMD:R_0805_HandSoldering</footprint>
      <libsource lib="device" part="R"/>
      <sheetpath names="/" tstamps="/"/>
      <tstamp>5AC4C599</tstamp>
    </comp>
    <comp ref="R18">
      <value>220R</value>
      <footprint>Resistors_SMD:R_0805_HandSoldering</footprint>
      <libsource lib="device" part="R"/>
      <sheetpath names="/" tstamps="/"/>
      <tstamp>5AC4C648</tstamp>
    </comp>
    <comp ref="J2">
      <value>FTDI</value>
      <footprint>Pin_Headers:Pin_Header_Angled_1x06_Pitch2.54mm</footprint>
      <libsource lib="jarvis_shield-cache" part="CONN_01X06"/>
      <sheetpath names="/" tstamps="/"/>
      <tstamp>5ACDBDD5</tstamp>
    </comp>
    <comp ref="C9">
      <value>100nF</value>
      <footprint>Capacitors_SMD:C_0805_HandSoldering</footprint>
      <libsource lib="device" part="C"/>
      <sheetpath names="/" tstamps="/"/>
      <tstamp>5ACDC853</tstamp>
    </comp>
    <comp ref="J4">
      <value>POWER</value>
      <footprint>Pin_Headers:Pin_Header_Straight_1x02_Pitch2.54mm</footprint>
      <libsource lib="jarvis_shield-cache" part="CONN_01X02"/>
      <sheetpath names="/" tstamps="/"/>
      <tstamp>5ACF12EF</tstamp>
    </comp>
    <comp ref="Q1">
      <value>MMBF170</value>
      <footprint>TO_SOT_Packages_SMD:SOT-23</footprint>
      <libsource lib="jarvis_shield-cache" part="MMBF170-RESCUE-jarvis_shield"/>
      <sheetpath names="/" tstamps="/"/>
      <tstamp>5AD6EA4C</tstamp>
    </comp>
    <comp ref="R7">
      <value>220</value>
      <footprint>Resistors_SMD:R_0805_HandSoldering</footprint>
      <libsource lib="device" part="R"/>
      <sheetpath names="/" tstamps="/"/>
      <tstamp>5A699CF6</tstamp>
    </comp>
    <comp ref="C10">
      <value>1pF</value>
      <footprint>Capacitors_SMD:C_0805_HandSoldering</footprint>
      <libsource lib="device" part="C"/>
      <sheetpath names="/" tstamps="/"/>
      <tstamp>5AD7425A</tstamp>
    </comp>
    <comp ref="C11">
      <value>1pF</value>
      <footprint>Capacitors_SMD:C_0805_HandSoldering</footprint>
      <libsource lib="device" part="C"/>
      <sheetpath names="/" tstamps="/"/>
      <tstamp>5AD74666</tstamp>
    </comp>
    <comp ref="J5">
      <value>USB_B_Micro</value>
      <footprint>Connectors:USB_Micro-B</footprint>
      <libsource lib="Connector" part="USB_B_Micro"/>
      <sheetpath names="/" tstamps="/"/>
      <tstamp>5AD74A67</tstamp>
    </comp>
    <comp ref="R20">
      <value>1K</value>
      <footprint>Resistors_SMD:R_0805_HandSoldering</footprint>
      <libsource lib="device" part="R"/>
      <sheetpath names="/" tstamps="/"/>
      <tstamp>5ADEEB1D</tstamp>
    </comp>
    <comp ref="R21">
      <value>1K</value>
      <footprint>Resistors_SMD:R_0805_HandSoldering</footprint>
      <libsource lib="device" part="R"/>
      <sheetpath names="/" tstamps="/"/>
      <tstamp>5ADEF1E5</tstamp>
    </comp>
    <comp ref="J6">
      <value>Wake-up/Upgrade</value>
      <footprint>Pin_Headers:Pin_Header_Straight_1x03_Pitch2.54mm</footprint>
      <libsource lib="device" part="Jumper_NC_Dual"/>
      <sheetpath names="/" tstamps="/"/>
      <tstamp>5AF2B7ED</tstamp>
    </comp>
    <comp ref="LS1">
      <value>Speaker</value>
      <footprint>Buzzers_Beepers:Buzzer_15x7.5RM7.6</footprint>
      <libsource lib="device" part="Speaker"/>
      <sheetpath names="/" tstamps="/"/>
      <tstamp>5AF2F124</tstamp>
    </comp>
    <comp ref="D7">
      <value>1N4148</value>
      <footprint>Diodes_SMD:D_0805</footprint>
      <libsource lib="pspice" part="DIODE"/>
      <sheetpath names="/" tstamps="/"/>
      <tstamp>5AF2F26A</tstamp>
    </comp>
    <comp ref="R22">
      <value>2K2</value>
      <footprint>Resistors_SMD:R_0805_HandSoldering</footprint>
      <libsource lib="device" part="R"/>
      <sheetpath names="/" tstamps="/"/>
      <tstamp>5AF2F311</tstamp>
    </comp>
    <comp ref="R23">
      <value>1K</value>
      <footprint>Resistors_SMD:R_0805_HandSoldering</footprint>
      <libsource lib="device" part="R"/>
      <sheetpath names="/" tstamps="/"/>
      <tstamp>5AF2F413</tstamp>
    </comp>
    <comp ref="Q2">
      <value>BC850W</value>
      <footprint>Package_TO_SOT_SMD:SOT-323_SC-70</footprint>
      <datasheet>https://www.mouser.es/datasheet/2/115/ds30039-892558.pdf</datasheet>
      <fields>
        <field name="Mouser REF">621-MMBT4401-13-F </field>
        <field name="Fabr REF">MMBT4401-13-F </field>
      </fields>
      <libsource lib="transistors" part="BC850W"/>
      <sheetpath names="/" tstamps="/"/>
      <tstamp>5AF322E5</tstamp>
    </comp>
    <comp ref="U5">
      <value>LM1117-3.3</value>
      <footprint>Package_TO_SOT_SMD:SOT-223-3_TabPin2</footprint>
      <libsource lib="regul" part="LM1117-3.3"/>
      <sheetpath names="/" tstamps="/"/>
      <tstamp>5B48A9F0</tstamp>
    </comp>
  </components>
  <libparts>
    <libpart lib="transistors" part="BC817W">
      <aliases>
        <alias>BC818W</alias>
        <alias>BC847W</alias>
        <alias>BC848W</alias>
        <alias>BC849W</alias>
        <alias>BC850W</alias>
      </aliases>
      <description>45V Vce, 0.8A Ic, NPN, SOT-23</description>
      <docs>http://www.fairchildsemi.com/ds/BC/BC817.pdf</docs>
      <footprints>
        <fp>SOT?323*</fp>
      </footprints>
      <fields>
        <field name="Reference">Q</field>
        <field name="Value">BC817W</field>
        <field name="Footprint">TO_SOT_Packages_SMD:SOT-323</field>
      </fields>
      <pins>
        <pin num="1" name="B" type="input"/>
        <pin num="2" name="E" type="passive"/>
        <pin num="3" name="C" type="passive"/>
      </pins>
    </libpart>
    <libpart lib="BH1750" part="BH1750">
      <fields>
        <field name="Reference">U</field>
        <field name="Value">BH1750</field>
        <field name="Footprint">MODULE</field>
        <field name="Datasheet">DOCUMENTATION</field>
      </fields>
      <pins>
        <pin num="1" name="VCC" type="power_in"/>
        <pin num="2" name="ADR" type="power_out"/>
        <pin num="3" name="GND" type="unspc"/>
        <pin num="4" name="SDA" type="unspc"/>
        <pin num="5" name="DVI" type="unspc"/>
        <pin num="6" name="SCL" type="unspc"/>
      </pins>
    </libpart>
    <libpart lib="device" part="C">
      <description>Unpolarized capacitor</description>
      <footprints>
        <fp>C_*</fp>
      </footprints>
      <fields>
        <field name="Reference">C</field>
        <field name="Value">C</field>
      </fields>
      <pins>
        <pin num="1" name="~" type="passive"/>
        <pin num="2" name="~" type="passive"/>
      </pins>
    </libpart>
    <libpart lib="jarvis_shield-cache" part="CONN_01X02">
      <footprints>
        <fp>Pin_Header_Straight_1X*</fp>
        <fp>Pin_Header_Angled_1X*</fp>
        <fp>Socket_Strip_Straight_1X*</fp>
        <fp>Socket_Strip_Angled_1X*</fp>
      </footprints>
      <fields>
        <field name="Reference">J</field>
        <field name="Value">CONN_01X02</field>
      </fields>
      <pins>
        <pin num="1" name="P1" type="passive"/>
        <pin num="2" name="P2" type="passive"/>
      </pins>
    </libpart>
    <libpart lib="jarvis_shield-cache" part="CONN_01X06">
      <footprints>
        <fp>Pin_Header_Straight_1X*</fp>
        <fp>Pin_Header_Angled_1X*</fp>
        <fp>Socket_Strip_Straight_1X*</fp>
        <fp>Socket_Strip_Angled_1X*</fp>
      </footprints>
      <fields>
        <field name="Reference">J</field>
        <field name="Value">CONN_01X06</field>
      </fields>
      <pins>
        <pin num="1" name="P1" type="passive"/>
        <pin num="2" name="P2" type="passive"/>
        <pin num="3" name="P3" type="passive"/>
        <pin num="4" name="P4" type="passive"/>
        <pin num="5" name="P5" type="passive"/>
        <pin num="6" name="P6" type="passive"/>
      </pins>
    </libpart>
    <libpart lib="device" part="C_Small">
      <description>Unpolarized capacitor</description>
      <footprints>
        <fp>C_*</fp>
      </footprints>
      <fields>
        <field name="Reference">C</field>
        <field name="Value">C_Small</field>
      </fields>
      <pins>
        <pin num="1" name="~" type="passive"/>
        <pin num="2" name="~" type="passive"/>
      </pins>
    </libpart>
    <libpart lib="pspice" part="DIODE">
      <fields>
        <field name="Reference">D</field>
        <field name="Value">DIODE</field>
      </fields>
      <pins>
        <pin num="1" name="K" type="input"/>
        <pin num="2" name="A" type="input"/>
      </pins>
    </libpart>
    <libpart lib="jarvis_shield-cache" part="ESP-12E">
      <footprints>
        <fp>ESP?12*</fp>
      </footprints>
      <fields>
        <field name="Reference">U</field>
        <field name="Value">ESP-12E</field>
        <field name="Footprint">RF_Modules:ESP-12E</field>
      </fields>
      <pins>
        <pin num="1" name="RST" type="input"/>
        <pin num="2" name="ADC" type="input"/>
        <pin num="3" name="EN/CH_PD" type="input"/>
        <pin num="4" name="GPIO16" type="BiDi"/>
        <pin num="5" name="GPIO14/HSPI_CLK" type="BiDi"/>
        <pin num="6" name="GPIO12/HSPI_MISO" type="BiDi"/>
        <pin num="7" name="GPIO13/HSPI_MOSI/UART0_CTS" type="BiDi"/>
        <pin num="8" name="VCC" type="power_in"/>
        <pin num="9" name="CS0" type="input"/>
        <pin num="10" name="MISO" type="BiDi"/>
        <pin num="11" name="GPIO9" type="BiDi"/>
        <pin num="12" name="GPIO10" type="BiDi"/>
        <pin num="13" name="MOSI" type="BiDi"/>
        <pin num="14" name="SCLK" type="BiDi"/>
        <pin num="15" name="GND" type="power_in"/>
        <pin num="16" name="GPIO15/MTDO/HSPICS/UART0_RTS" type="BiDi"/>
        <pin num="17" name="GPIO2/UART1_TXD" type="BiDi"/>
        <pin num="18" name="GPIO0" type="BiDi"/>
        <pin num="19" name="GPIO4" type="BiDi"/>
        <pin num="20" name="GPIO5" type="BiDi"/>
        <pin num="21" name="UART0_RXD/GPIO3" type="BiDi"/>
        <pin num="22" name="UART0_TXD/GPIO1" type="BiDi"/>
      </pins>
    </libpart>
    <libpart lib="device" part="Jumper_NC_Dual">
      <description>Dual Jumper, normally closed</description>
      <fields>
        <field name="Reference">JP</field>
        <field name="Value">Jumper_NC_Dual</field>
      </fields>
      <pins>
        <pin num="1" name="1" type="passive"/>
        <pin num="2" name="2" type="passive"/>
        <pin num="3" name="3" type="passive"/>
      </pins>
    </libpart>
    <libpart lib="device" part="Jumper_NO_Small">
      <description>Jumper, normally open</description>
      <fields>
        <field name="Reference">JP</field>
        <field name="Value">Jumper_NO_Small</field>
      </fields>
      <pins>
        <pin num="1" name="1" type="passive"/>
        <pin num="2" name="2" type="passive"/>
      </pins>
    </libpart>
    <libpart lib="device" part="LED">
      <description>LED generic</description>
      <footprints>
        <fp>LED*</fp>
      </footprints>
      <fields>
        <field name="Reference">D</field>
        <field name="Value">LED</field>
      </fields>
      <pins>
        <pin num="1" name="K" type="passive"/>
        <pin num="2" name="A" type="passive"/>
      </pins>
    </libpart>
    <libpart lib="regul" part="LM1117-1.8">
      <aliases>
        <alias>LM1117-2.5</alias>
        <alias>LM1117-3.3</alias>
        <alias>LM1117-5.0</alias>
        <alias>TLV1117-15</alias>
        <alias>TLV1117-18</alias>
        <alias>TLV1117-25</alias>
        <alias>TLV1117-33</alias>
        <alias>TLV1117-50</alias>
      </aliases>
      <description>800mA Low-Dropout Linear Regulator, 1.8V fixed output, TO-220/TO-252/TO-263/SOT-223</description>
      <docs>http://www.ti.com/lit/ds/symlink/lm1117.pdf</docs>
      <footprints>
        <fp>SOT?223*</fp>
        <fp>TO?263*</fp>
        <fp>TO?252*</fp>
        <fp>TO?220*</fp>
      </footprints>
      <fields>
        <field name="Reference">U</field>
        <field name="Value">LM1117-1.8</field>
      </fields>
      <pins>
        <pin num="1" name="GND" type="power_in"/>
        <pin num="2" name="VO" type="power_out"/>
        <pin num="3" name="VI" type="power_in"/>
      </pins>
    </libpart>
    <libpart lib="jarvis_shield-cache" part="MMBF170-RESCUE-jarvis_shield">
      <footprints>
        <fp>SOT-23*</fp>
      </footprints>
      <fields>
        <field name="Reference">Q</field>
        <field name="Value">MMBF170-RESCUE-jarvis_shield</field>
        <field name="Footprint">TO_SOT_Packages_SMD:SOT-23</field>
      </fields>
      <pins>
        <pin num="1" name="G" type="input"/>
        <pin num="2" name="S" type="passive"/>
        <pin num="3" name="D" type="passive"/>
      </pins>
    </libpart>
    <libpart lib="LED" part="Neopixel_THT">
      <description>WS2812B ("Neopixel") digital RGB LED, 5mm/8mm LED package</description>
      <docs>https://www.adafruit.com/product/1938</docs>
      <footprints>
        <fp>LED*D5.0mm*</fp>
        <fp>LED*D8.0mm*</fp>
      </footprints>
      <fields>
        <field name="Reference">D</field>
        <field name="Value">Neopixel_THT</field>
      </fields>
      <pins>
        <pin num="1" name="DOUT" type="output"/>
        <pin num="2" name="GND" type="power_in"/>
        <pin num="3" name="5V" type="power_in"/>
        <pin num="4" name="DIN" type="input"/>
      </pins>
    </libpart>
    <libpart lib="device" part="R">
      <description>Resistor</description>
      <footprints>
        <fp>R_*</fp>
        <fp>R_*</fp>
      </footprints>
      <fields>
        <field name="Reference">R</field>
        <field name="Value">R</field>
      </fields>
      <pins>
        <pin num="1" name="~" type="passive"/>
        <pin num="2" name="~" type="passive"/>
      </pins>
    </libpart>
    <libpart lib="SHT30-DIS-B" part="SHT30-DIS-B">
      <fields>
        <field name="Reference">U</field>
        <field name="Value">SHT30-DIS-B</field>
        <field name="Footprint">DFN250X250X100-9N</field>
        <field name="Datasheet">Good</field>
        <field name="Field4">2.15 USD</field>
        <field name="Field5">SENSOR HUMID/TEMP 5V I2C 3% SMD</field>
        <field name="Field6">DFN-8 Sensirion</field>
        <field name="Field7">SHT30-DIS-B</field>
        <field name="Field8">Sensirion</field>
      </fields>
      <pins>
        <pin num="1" name="SDA" type="BiDi"/>
        <pin num="2" name="ADDR" type="input"/>
        <pin num="3" name="ALERT" type="output"/>
        <pin num="4" name="SCL" type="BiDi"/>
        <pin num="5" name="VDD" type="power_in"/>
        <pin num="6" name="~RESET~" type="input"/>
        <pin num="7" name="R" type="passive"/>
        <pin num="8" name="VSS" type="passive"/>
        <pin num="9" name="EXP" type="passive"/>
      </pins>
    </libpart>
    <libpart lib="Switch" part="SW_Push">
      <description>Push button switch, generic, two pins</description>
      <fields>
        <field name="Reference">SW</field>
        <field name="Value">SW_Push</field>
      </fields>
      <pins>
        <pin num="1" name="1" type="passive"/>
        <pin num="2" name="2" type="passive"/>
      </pins>
    </libpart>
    <libpart lib="jarvis_shield-cache" part="Screw_Terminal_1x02">
      <footprints>
        <fp>bornier2</fp>
        <fp>TerminalBlock*2pol</fp>
      </footprints>
      <fields>
        <field name="Reference">J</field>
        <field name="Value">Screw_Terminal_1x02</field>
      </fields>
      <pins>
        <pin num="1" name="~" type="passive"/>
        <pin num="2" name="~" type="passive"/>
      </pins>
    </libpart>
    <libpart lib="device" part="Speaker">
      <description>speaker </description>
      <fields>
        <field name="Reference">LS</field>
        <field name="Value">Speaker</field>
      </fields>
      <pins>
        <pin num="1" name="1" type="input"/>
        <pin num="2" name="2" type="input"/>
      </pins>
    </libpart>
    <libpart lib="conn" part="USB_A">
      <description>USB Type A connector</description>
      <footprints>
        <fp>USB*</fp>
      </footprints>
      <fields>
        <field name="Reference">J</field>
        <field name="Value">USB_A</field>
      </fields>
      <pins>
        <pin num="1" name="VBUS" type="power_in"/>
        <pin num="2" name="D-" type="passive"/>
        <pin num="3" name="D+" type="passive"/>
        <pin num="4" name="GND" type="power_in"/>
        <pin num="5" name="Shield" type="passive"/>
      </pins>
    </libpart>
    <libpart lib="Connector" part="USB_B_Micro">
      <aliases>
        <alias>USB_B_Mini</alias>
      </aliases>
      <description>USB Micro Type B connector</description>
      <docs>~</docs>
      <footprints>
        <fp>USB*</fp>
      </footprints>
      <fields>
        <field name="Reference">J</field>
        <field name="Value">USB_B_Micro</field>
      </fields>
      <pins>
        <pin num="1" name="VBUS" type="power_out"/>
        <pin num="2" name="D-" type="passive"/>
        <pin num="3" name="D+" type="passive"/>
        <pin num="4" name="ID" type="passive"/>
        <pin num="5" name="GND" type="power_out"/>
        <pin num="6" name="Shield" type="passive"/>
      </pins>
    </libpart>
    <libpart lib="jarvis_shield-rescue" part="oledDisplay-RESCUE-jarvis_shield">
      <fields>
        <field name="Reference">U</field>
        <field name="Value">oledDisplay-RESCUE-jarvis_shield</field>
        <field name="Footprint">MODULE</field>
        <field name="Datasheet">DOCUMENTATION</field>
      </fields>
      <pins>
        <pin num="1" name="GND" type="power_in"/>
        <pin num="2" name="Vcc" type="output"/>
        <pin num="3" name="SCL" type="BiDi"/>
        <pin num="4" name="SDA" type="BiDi"/>
      </pins>
    </libpart>
  </libparts>
  <libraries>
    <library logical="device">
      <uri>/usr/share/kicad/library/device.lib</uri>
    </library>
    <library logical="jarvis_shield-rescue">
      <uri>/media/david/Nano/Nano/jarwis/jarvis_shield-rescue.lib</uri>
    </library>
    <library logical="transistors">
      <uri>/usr/share/kicad/library/transistors.lib</uri>
    </library>
    <library logical="conn">
      <uri>/usr/share/kicad/library/conn.lib</uri>
    </library>
    <library logical="regul">
      <uri>/usr/share/kicad/library/regul.lib</uri>
    </library>
    <library logical="Switch">
      <uri>/usr/share/kicad/library/Switch.lib</uri>
    </library>
    <library logical="Connector">
      <uri>/usr/share/kicad/library/Connector.lib</uri>
    </library>
    <library logical="pspice">
      <uri>/usr/share/kicad/library/pspice.lib</uri>
    </library>
    <library logical="LED">
      <uri>/usr/share/kicad/library/LED.lib</uri>
    </library>
    <library logical="BH1750">
      <uri>/usr/share/kicad/library/BH1750.lib</uri>
    </library>
    <library logical="jarvis_shield-cache">
      <uri>/media/david/Nano/Nano/jarwis/jarvis_shield-cache.lib</uri>
    </library>
    <library logical="SHT30-DIS-B">
      <uri>/usr/share/kicad/library/SHT30-DIS-B.lib</uri>
    </library>
  </libraries>
  <nets>
    <net code="1" name="D2">
      <node ref="U4" pin="17"/>
    </net>
    <net code="2" name="D9">
      <node ref="U4" pin="11"/>
      <node ref="R22" pin="2"/>
    </net>
    <net code="3" name="D10">
      <node ref="U4" pin="12"/>
    </net>
    <net code="4" name="A0">
      <node ref="R16" pin="1"/>
      <node ref="R15" pin="1"/>
      <node ref="R18" pin="1"/>
    </net>
    <net code="5" name="RESET">
      <node ref="J6" pin="1"/>
      <node ref="C9" pin="1"/>
      <node ref="J2" pin="1"/>
    </net>
    <net code="6" name="TX">
      <node ref="U4" pin="22"/>
      <node ref="J2" pin="2"/>
    </net>
    <net code="7" name="RX">
      <node ref="J2" pin="3"/>
      <node ref="U4" pin="21"/>
    </net>
    <net code="8" name="Net-(J2-Pad5)">
      <node ref="J2" pin="5"/>
    </net>
    <net code="9" name="+3V3">
      <node ref="SW3" pin="1"/>
      <node ref="SW2" pin="1"/>
      <node ref="SW1" pin="1"/>
      <node ref="C2" pin="1"/>
      <node ref="C11" pin="1"/>
      <node ref="U5" pin="2"/>
      <node ref="U2" pin="5"/>
      <node ref="U3" pin="2"/>
      <node ref="R20" pin="2"/>
      <node ref="J6" pin="3"/>
      <node ref="R17" pin="2"/>
      <node ref="C7" pin="2"/>
      <node ref="U1" pin="1"/>
      <node ref="C8" pin="2"/>
      <node ref="R9" pin="2"/>
      <node ref="J4" pin="1"/>
      <node ref="J2" pin="4"/>
      <node ref="U4" pin="8"/>
      <node ref="R10" pin="2"/>
    </net>
    <net code="10" name="GND">
      <node ref="C5" pin="2"/>
      <node ref="U2" pin="7"/>
      <node ref="U2" pin="2"/>
      <node ref="U2" pin="8"/>
      <node ref="C7" pin="1"/>
      <node ref="C8" pin="1"/>
      <node ref="R16" pin="2"/>
      <node ref="Q1" pin="2"/>
      <node ref="U4" pin="15"/>
      <node ref="D1" pin="1"/>
      <node ref="J5" pin="5"/>
      <node ref="C11" pin="2"/>
      <node ref="C10" pin="2"/>
      <node ref="C6" pin="2"/>
      <node ref="C3" pin="2"/>
      <node ref="C4" pin="2"/>
      <node ref="U3" pin="1"/>
      <node ref="D5" pin="2"/>
      <node ref="D4" pin="2"/>
      <node ref="C2" pin="2"/>
      <node ref="D6" pin="2"/>
      <node ref="U1" pin="3"/>
      <node ref="R8" pin="2"/>
      <node ref="C1" pin="2"/>
      <node ref="R6" pin="2"/>
      <node ref="R2" pin="1"/>
      <node ref="R3" pin="1"/>
      <node ref="R4" pin="1"/>
      <node ref="D3" pin="2"/>
      <node ref="SW4" pin="1"/>
      <node ref="U5" pin="1"/>
      <node ref="R21" pin="1"/>
      <node ref="Q2" pin="2"/>
      <node ref="J4" pin="2"/>
      <node ref="R19" pin="2"/>
      <node ref="J2" pin="6"/>
    </net>
    <net code="11" name="Net-(R18-Pad2)">
      <node ref="R18" pin="2"/>
      <node ref="R19" pin="1"/>
      <node ref="U4" pin="2"/>
    </net>
    <net code="12" name="D14">
      <node ref="U4" pin="5"/>
      <node ref="R3" pin="2"/>
      <node ref="SW2" pin="2"/>
    </net>
    <net code="13" name="D12">
      <node ref="SW1" pin="2"/>
      <node ref="U4" pin="6"/>
      <node ref="R2" pin="2"/>
    </net>
    <net code="14" name="D16">
      <node ref="U4" pin="4"/>
      <node ref="R1" pin="1"/>
    </net>
    <net code="15" name="D13">
      <node ref="U4" pin="7"/>
      <node ref="D3" pin="4"/>
    </net>
    <net code="16" name="D0">
      <node ref="J6" pin="2"/>
      <node ref="U4" pin="18"/>
    </net>
    <net code="17" name="Net-(C9-Pad2)">
      <node ref="U4" pin="1"/>
      <node ref="C9" pin="2"/>
      <node ref="SW4" pin="2"/>
    </net>
    <net code="18" name="SCL">
      <node ref="U2" pin="4"/>
      <node ref="U3" pin="3"/>
      <node ref="R17" pin="1"/>
      <node ref="U4" pin="20"/>
      <node ref="U1" pin="6"/>
    </net>
    <net code="19" name="SDA">
      <node ref="U1" pin="4"/>
      <node ref="U2" pin="1"/>
      <node ref="U3" pin="4"/>
      <node ref="U4" pin="19"/>
      <node ref="R10" pin="1"/>
    </net>
    <net code="20" name="Net-(C1-Pad1)">
      <node ref="C1" pin="1"/>
      <node ref="U1" pin="5"/>
      <node ref="R9" pin="1"/>
    </net>
    <net code="21" name="Net-(R8-Pad1)">
      <node ref="U1" pin="2"/>
      <node ref="R8" pin="1"/>
    </net>
    <net code="22" name="Net-(R20-Pad1)">
      <node ref="U4" pin="3"/>
      <node ref="R20" pin="1"/>
    </net>
    <net code="23" name="D15">
      <node ref="U4" pin="16"/>
      <node ref="R21" pin="2"/>
      <node ref="SW3" pin="2"/>
      <node ref="R4" pin="2"/>
    </net>
    <net code="24" name="Net-(U4-Pad9)">
      <node ref="U4" pin="9"/>
    </net>
    <net code="25" name="Net-(U4-Pad10)">
      <node ref="U4" pin="10"/>
    </net>
    <net code="26" name="Net-(U4-Pad13)">
      <node ref="U4" pin="13"/>
    </net>
    <net code="27" name="Net-(U4-Pad14)">
      <node ref="U4" pin="14"/>
    </net>
    <net code="28" name="+5V">
      <node ref="R23" pin="1"/>
      <node ref="R12" pin="1"/>
      <node ref="R13" pin="1"/>
      <node ref="R11" pin="1"/>
      <node ref="J5" pin="1"/>
      <node ref="U5" pin="3"/>
      <node ref="J3" pin="1"/>
      <node ref="LS1" pin="1"/>
      <node ref="R15" pin="2"/>
      <node ref="C10" pin="1"/>
      <node ref="J1" pin="1"/>
      <node ref="D2" pin="2"/>
    </net>
    <net code="29" name="Net-(D7-Pad1)">
      <node ref="R23" pin="2"/>
      <node ref="D7" pin="1"/>
    </net>
    <net code="30" name="Net-(Q2-Pad1)">
      <node ref="R22" pin="1"/>
      <node ref="Q2" pin="1"/>
    </net>
    <net code="31" name="Net-(D7-Pad2)">
      <node ref="D7" pin="2"/>
      <node ref="Q2" pin="3"/>
      <node ref="LS1" pin="2"/>
    </net>
    <net code="33" name="Net-(J5-Pad6)">
      <node ref="J5" pin="6"/>
    </net>
    <net code="34" name="Net-(J5-Pad4)">
      <node ref="J5" pin="4"/>
    </net>
    <net code="35" name="Net-(J5-Pad2)">
      <node ref="J5" pin="2"/>
    </net>
    <net code="36" name="Net-(J5-Pad3)">
      <node ref="J5" pin="3"/>
    </net>
    <net code="37" name="Net-(J3-Pad3)">
      <node ref="J3" pin="3"/>
    </net>
    <net code="38" name="Net-(C5-Pad1)">
      <node ref="R13" pin="2"/>
      <node ref="C5" pin="1"/>
      <node ref="D5" pin="3"/>
    </net>
    <net code="39" name="Net-(J3-Pad2)">
      <node ref="J3" pin="2"/>
    </net>
    <net code="40" name="Net-(J3-Pad5)">
      <node ref="J3" pin="5"/>
    </net>
    <net code="41" name="Net-(C4-Pad1)">
      <node ref="D4" pin="3"/>
      <node ref="R12" pin="2"/>
      <node ref="C4" pin="1"/>
    </net>
    <net code="42" name="Net-(R14-Pad1)">
      <node ref="R14" pin="1"/>
    </net>
    <net code="43" name="Net-(D6-Pad1)">
      <node ref="D6" pin="1"/>
    </net>
    <net code="44" name="Net-(U2-Pad3)">
      <node ref="U2" pin="3"/>
    </net>
    <net code="45" name="Net-(U2-Pad6)">
      <node ref="U2" pin="6"/>
    </net>
    <net code="46" name="Net-(U2-Pad9)">
      <node ref="U2" pin="9"/>
    </net>
    <net code="47" name="D7">
      <node ref="R5" pin="2"/>
    </net>
    <net code="48" name="Net-(D1-Pad2)">
      <node ref="R1" pin="2"/>
      <node ref="D1" pin="2"/>
    </net>
    <net code="49" name="Net-(C6-Pad1)">
      <node ref="D6" pin="3"/>
      <node ref="C6" pin="1"/>
      <node ref="R14" pin="2"/>
    </net>
    <net code="50" name="Net-(D5-Pad1)">
      <node ref="D6" pin="4"/>
      <node ref="D5" pin="1"/>
    </net>
    <net code="51" name="Net-(D3-Pad1)">
      <node ref="D3" pin="1"/>
      <node ref="D4" pin="4"/>
    </net>
    <net code="52" name="Net-(D4-Pad1)">
      <node ref="D4" pin="1"/>
      <node ref="D5" pin="4"/>
    </net>
    <net code="53" name="Net-(D2-Pad1)">
      <node ref="D2" pin="1"/>
      <node ref="R7" pin="1"/>
    </net>
    <net code="54" name="Net-(JP1-Pad2)">
      <node ref="JP1" pin="2"/>
      <node ref="R7" pin="2"/>
      <node ref="Q1" pin="3"/>
    </net>
    <net code="55" name="Vout">
      <node ref="J1" pin="2"/>
      <node ref="JP1" pin="1"/>
      <node ref="J3" pin="4"/>
    </net>
    <net code="56" name="Net-(Q1-Pad1)">
      <node ref="Q1" pin="1"/>
      <node ref="R5" pin="1"/>
      <node ref="R6" pin="1"/>
    </net>
    <net code="57" name="Net-(C3-Pad1)">
      <node ref="R11" pin="2"/>
      <node ref="D3" pin="3"/>
      <node ref="C3" pin="1"/>
    </net>
  </nets>
</export>
